setuptools_git_ls_files.py
setuptools_git_ls_files-0.1.2.dist-info/LICENSE
setuptools_git_ls_files-0.1.2.dist-info/METADATA
setuptools_git_ls_files-0.1.2.dist-info/WHEEL
setuptools_git_ls_files-0.1.2.dist-info/entry_points.txt
setuptools_git_ls_files-0.1.2.dist-info/top_level.txt
setuptools_git_ls_files-0.1.2.dist-info/zip-safe
setuptools_git_ls_files-0.1.2.dist-info/RECORD
